asp/__init__.py
asp/advice_builder.py
asp/weaver.py
drawer/__init__.py
drawer/advice_builder.py
drawer/weaver.py
drawer-0.1a4.dist-info/METADATA
drawer-0.1a4.dist-info/WHEEL
drawer-0.1a4.dist-info/top_level.txt
drawer-0.1a4.dist-info/RECORD
